MEDFORD/medford.py
MEDFORD/mfdglobals.py
MEDFORD/models/generics.py
MEDFORD/objs/__init__.py
MEDFORD/objs/dictionizer.py
MEDFORD/objs/linecollections.py
MEDFORD/objs/linecollector.py
MEDFORD/objs/linereader.py
MEDFORD/objs/lines.py
MEDFORD/submodules/mfdvalidator/__init__.py
MEDFORD/submodules/mfdvalidator/errors.py
MEDFORD/submodules/mfdvalidator/notice.py
MEDFORD/submodules/mfdvalidator/validator.py
medford-2.0.0.dist-info/LICENSE
medford-2.0.0.dist-info/METADATA
medford-2.0.0.dist-info/WHEEL
medford-2.0.0.dist-info/entry_points.txt
medford-2.0.0.dist-info/top_level.txt
medford-2.0.0.dist-info/RECORD
