Metadata-Version: 2.1
Name: medford
Version: 2.0.0
Summary: The MEDFORD Command Line tool for validating & compiling medford research metadata files.
Home-page: https://github.com/TuftsBCB/medford
Author: Polina Shpilker
Author-email: polina.shpilker@tufts.edu
Classifier: Programming Language :: Python :: 3
Classifier: License :: OSI Approved :: MIT License
License-File: LICENSE
Requires-Dist: pydantic ==2.4.2
